venvctrl/__init__.py
venvctrl/api.py
venvctrl/cli/__init__.py
venvctrl/cli/relocate.py
venvctrl/venv/__init__.py
venvctrl/venv/base.py
venvctrl/venv/command.py
venvctrl/venv/create.py
venvctrl/venv/pip.py
venvctrl/venv/relocate.py
venvctrl-0.10.0.dist-info/LICENSE
venvctrl-0.10.0.dist-info/METADATA
venvctrl-0.10.0.dist-info/WHEEL
venvctrl-0.10.0.dist-info/entry_points.txt
venvctrl-0.10.0.dist-info/top_level.txt
venvctrl-0.10.0.dist-info/RECORD
