Metadata-Version: 2.2
Name: venvctrl
Version: 0.10.0
Summary: API for virtual environments.
Home-page: https://github.com/kevinconway/venvctrl
Author: Kevin Conway
Author-email: kevinjacobconway@gmail.com
License: MIT
License-File: LICENSE
Requires-Dist: virtualenv
Dynamic: author
Dynamic: author-email
Dynamic: description
Dynamic: home-page
Dynamic: license
Dynamic: requires-dist
Dynamic: summary
